bvbabel/__init__.py
bvbabel/dmr.py
bvbabel/dwi.py
bvbabel/fbr.py
bvbabel/fmr.py
bvbabel/glm.py
bvbabel/gtc.py
bvbabel/map.py
bvbabel/msk.py
bvbabel/mtc.py
bvbabel/obj.py
bvbabel/poi.py
bvbabel/prt.py
bvbabel/roi.py
bvbabel/sdm.py
bvbabel/smp.py
bvbabel/srf.py
bvbabel/ssm.py
bvbabel/stc.py
bvbabel/trf.py
bvbabel/utils.py
bvbabel/v16.py
bvbabel/vmp.py
bvbabel/vmr.py
bvbabel/voi.py
bvbabel/vtc.py
bvbabel-0.2.0.dist-info/LICENSE
bvbabel-0.2.0.dist-info/METADATA
bvbabel-0.2.0.dist-info/WHEEL
bvbabel-0.2.0.dist-info/top_level.txt
bvbabel-0.2.0.dist-info/RECORD
