Metadata-Version: 2.1
Name: bvbabel
Version: 0.2.0
Summary: A lightweight Python library for reading and writing BrainVoyager file formats.
Home-page: https://github.com/ofgulban/bvbabel
Download-URL: https://github.com/ofgulban/bvbabel/archive/0.2.0.tar.gz
Author: Omer Faruk Gulban
Author-email: gulban@brainvoyager.com
License: MIT
License-File: LICENSE
Requires-Dist: numpy
